<?xml version="1.0" encoding="UTF-8" standalone="yes"?>




<item> 
<title>[COLOR yellow]_**_ [/COLOR][COLOR  skyblue] Ray donovan [/COLOR][COLOR yellow]_**_[/COLOR]</title>
<link>http://Ignoreme</link>
<thumbnail></thumbnail>
<fanart></fanart>
<externallink>https://raw.githubusercontent.com/lokiyotnt69/DARKNIGHT66/master/SERIES/Ray%20donovan.xml</externallink>	
</item> 


<item> 
<title>[COLOR yellow]_**_ [/COLOR][COLOR  skyblue] Real Humans [/COLOR][COLOR yellow]_**_[/COLOR]</title>
<link>http://Ignoreme</link>
<thumbnail></thumbnail>
<fanart></fanart>
<externallink>https://raw.githubusercontent.com/lokiyotnt69/DARKNIGHT66/master/SERIES/realhumans.xml</externallink>	
</item> 

<item> 
<title>[COLOR yellow]_**_ [/COLOR][COLOR  skyblue] Rebelde [/COLOR][COLOR yellow]_**_[/COLOR]</title>
<link>http://Ignoreme</link>
<thumbnail></thumbnail>
<fanart></fanart>
<externallink>https://raw.githubusercontent.com/lokiyotnt69/DARKNIGHT66/master/SERIES/Rebelde.xml</externallink>	
</item> 

<item> 
<title>[COLOR yellow]_**_ [/COLOR][COLOR  skyblue] Rebellion [/COLOR][COLOR yellow]_**_[/COLOR]</title>
<link>http://Ignoreme</link>
<thumbnail></thumbnail>
<fanart></fanart>
<externallink>https://raw.githubusercontent.com/lokiyotnt69/DARKNIGHT66/master/SERIES/Rebellion.xml</externallink>	
</item> 



<item> 
<title>[COLOR yellow]_**_ [/COLOR][COLOR  skyblue] Rehenes [/COLOR][COLOR yellow]_**_[/COLOR]</title>
<link>http://Ignoreme</link>
<thumbnail></thumbnail>
<fanart></fanart>
<externallink>https://raw.githubusercontent.com/lokiyotnt69/DARKNIGHT66/master/SERIES/Rehenes.xml</externallink>	
</item> 

<item> 
<title>[COLOR yellow]_**_ [/COLOR][COLOR  skyblue] Reign [/COLOR][COLOR yellow]_**_[/COLOR]</title>
<link>http://Ignoreme</link>
<thumbnail></thumbnail>
<fanart></fanart>
<externallink>https://raw.githubusercontent.com/lokiyotnt69/DARKNIGHT66/master/SERIES/Reign.xml</externallink>	
</item> 

<item> 
<title>[COLOR yellow]_**_ [/COLOR][COLOR  skyblue] Reinas [/COLOR][COLOR yellow]_**_[/COLOR]</title>
<link>http://Ignoreme</link>
<thumbnail></thumbnail>
<fanart></fanart>
<externallink>https://raw.githubusercontent.com/lokiyotnt69/DARKNIGHT66/master/SERIES/Reinas.xml</externallink>	
</item> 

<item> 
<title>[COLOR yellow]_**_ [/COLOR][COLOR  skyblue] Resurrection [/COLOR][COLOR yellow]_**_[/COLOR]</title>
<link>http://Ignoreme</link>
<thumbnail></thumbnail>
<fanart></fanart>
<externallink>https://raw.githubusercontent.com/lokiyotnt69/DARKNIGHT66/master/SERIES/Resurrection%20.xml</externallink>	
</item> 

<item> 
<title>[COLOR yellow]_**_ [/COLOR][COLOR  skyblue] Revenge [/COLOR][COLOR yellow]_**_[/COLOR]</title>
<link>http://Ignoreme</link>
<thumbnail></thumbnail>
<fanart></fanart>
<externallink>https://raw.githubusercontent.com/lokiyotnt69/DARKNIGHT66/master/SERIES/revenge.xml</externallink>	
</item> 

<item> 
<title>[COLOR yellow]_**_ [/COLOR][COLOR  skyblue] Revolution [/COLOR][COLOR yellow]_**_[/COLOR]</title>
<link>http://Ignoreme</link>
<thumbnail></thumbnail>
<fanart></fanart>
<externallink>https://raw.githubusercontent.com/lokiyotnt69/DARKNIGHT66/master/SERIES/Revolution.xml</externallink>	
</item> 


<item> 
<title>[COLOR yellow]_**_ [/COLOR][COLOR  skyblue] Rick y morty [/COLOR][COLOR yellow]_**_[/COLOR]</title>
<link>http://Ignoreme</link>
<thumbnail></thumbnail>
<fanart></fanart>
<externallink>https://raw.githubusercontent.com/lokiyotnt69/DARKNIGHT66/master/SERIES/Rick%20y%20morty.xml</externallink>	
</item> 

<item> 
<title>[COLOR yellow]_**_ [/COLOR][COLOR  skyblue] Rita [/COLOR][COLOR yellow]_**_[/COLOR]</title>
<link>http://Ignoreme</link>
<thumbnail></thumbnail>
<fanart></fanart>
<externallink>https://raw.githubusercontent.com/lokiyotnt69/DARKNIGHT66/master/SERIES/Rita.xml</externallink>	
</item> 

<item> 
<title>[COLOR yellow]_**_ [/COLOR][COLOR  skyblue] Riverdale [/COLOR][COLOR yellow]_**_[/COLOR]</title>
<link>http://Ignoreme</link>
<thumbnail></thumbnail>
<fanart></fanart>
<externallink>https://raw.githubusercontent.com/lokiyotnt69/DARKNIGHT66/master/SERIES/Riverdale%20.xml</externallink>	
</item> 

<item> 
<title>[COLOR yellow]_**_ [/COLOR][COLOR  skyblue] Riviera [/COLOR][COLOR yellow]_**_[/COLOR]</title>
<link>http://Ignoreme</link>
<thumbnail></thumbnail>
<fanart></fanart>
<externallink></externallink>	
</item> 

<item> 
<title>[COLOR yellow]_**_ [/COLOR][COLOR  skyblue] Roma [/COLOR][COLOR yellow]_**_[/COLOR]</title>
<link>http://Ignoreme</link>
<thumbnail></thumbnail>
<fanart></fanart>
<externallink></externallink>	
</item> 

<item> 
<title>[COLOR yellow]_**_ [/COLOR][COLOR  skyblue] Roma Criminal [/COLOR][COLOR yellow]_**_[/COLOR]</title>
<link>http://Ignoreme</link>
<thumbnail></thumbnail>
<fanart></fanart>
<externallink></externallink>	
</item> 

<item> 
<title>[COLOR yellow]_**_ [/COLOR][COLOR  skyblue] Rosewood [/COLOR][COLOR yellow]_**_[/COLOR]</title>
<link>http://Ignoreme</link>
<thumbnail></thumbnail>
<fanart></fanart>
<externallink></externallink>	
</item> 
